{
  "data": "2026-07-01 08:17",
  "voto_fiducia": 87,
  "trend_fiducia": "▼",
  "sintesi": "Giro 1/7 08:17. Voto 87 (▼ da 88): KPI live REST (= business, stallo 165,8h, 168h ~2,2h ~10:30). Escalation v5 🟢. Sprint 1 ok Nicola integrato; push PR 403 documentato. Nessun errore grounding. MCP cieco, REST OK.",
  "verifiche": {
    "entita": "ok",
    "numeri": "ok (live REST 08:17, clmpyfvpvfjgeviworth)",
    "coerenza": "ok (allineato DECISIONI/chat 1/7 07:30-07:41)",
    "semaforo": "ok",
    "qualita": "ok",
    "benchmark": "n/a"
  },
  "errori": [],
  "domande_per_nicola": [
    {
      "domanda": "Ordine zombie €19,05 (Pane Quotidiano, buyer 348 642 1766): accetti e consegni (A) o annulli (B)?",
      "perche_serve": "Unica via 1ª transazione reale; ~2,2h a soglia 168h (~10:30).",
      "se_rispondi": "Eseguo pacchetto operations opzione scelta.",
      "gravita": "alta"
    },
    {
      "domanda": "Push + PR Sprint 1 su mycity: push manuale, ok #14 token, o aspetti?",
      "perche_serve": "Codice pronto 07:30 — PR non creata per 403 PAT.",
      "se_rispondi": "Tech pusha branch o accoda deploy post-PR.",
      "gravita": "alta"
    },
    {
      "domanda": "Quanti negozi inserisci il 6/7 e quali nomi?",
      "perche_serve": "Checklist onboarding pronta — serve lista per preparare catalogo/contratti.",
      "se_rispondi": "AD personalizza checklist per ogni bottega.",
      "gravita": "media"
    }
  ],
  "punti_ciechi": [
    "Supabase MCP cieco (REST fallback OK)",
    "PostHog non collegato",
    "Competitor non ricontrollati (cadenza settimanale)"
  ],
  "miglioramenti_prossimo_giro": [
    "Se supera 168h: escalation binaria in DECISIONI",
    "Verificare esito push Sprint 1"
  ],
  "salute_macchina": {
    "supabase_marketplace": "REST live ✅ · MCP cieco ❌",
    "supabase_memoria": "env presente ✅ · POST briefings OK",
    "stripe": "non verificato in sessione",
    "posthog": "non collegato ❌",
    "dati_freschi": true,
    "sensori_attivi": 2
  }
}
